LICENSE
concourseatom/__init__.py
concourseatom/models.py
concourseatom/tools.py
concourseatom-0.3.0.dist-info/entry_points.txt
concourseatom-0.3.0.dist-info/LICENSE
concourseatom-0.3.0.dist-info/WHEEL
concourseatom-0.3.0.dist-info/METADATA
concourseatom-0.3.0.dist-info/RECORD
